yyx_tools/__init__.py
yyx_tools/file.py
yyx_tools/list.py
yyx_tools/utils.py
yyx_tools/video.py
yyxtools/__init__.py
yyxtools/file.py
yyxtools/list.py
yyxtools/utils.py
yyxtools/video.py
yyxtools-0.0.1.dist-info/LICENSE
yyxtools-0.0.1.dist-info/METADATA
yyxtools-0.0.1.dist-info/WHEEL
yyxtools-0.0.1.dist-info/top_level.txt
yyxtools-0.0.1.dist-info/RECORD
